chemicals/__init__.py
chemicals/acentric.py
chemicals/air.py
chemicals/combustion.py
chemicals/critical.py
chemicals/data_reader.py
chemicals/dipole.py
chemicals/dippr.py
chemicals/elements.py
chemicals/environment.py
chemicals/exceptions.py
chemicals/flash_basic.py
chemicals/heat_capacity.py
chemicals/iapws.py
chemicals/identifiers.py
chemicals/interface.py
chemicals/lennard_jones.py
chemicals/miscdata.py
chemicals/molecular_geometry.py
chemicals/numba.py
chemicals/numba_vectorized.py
chemicals/permittivity.py
chemicals/phase_change.py
chemicals/py.typed
chemicals/rachford_rice.py
chemicals/reaction.py
chemicals/refractivity.py
chemicals/safety.py
chemicals/solubility.py
chemicals/temperature.py
chemicals/thermal_conductivity.py
chemicals/triple.py
chemicals/units.py
chemicals/utils.py
chemicals/vapor_pressure.py
chemicals/vectorized.py
chemicals/virial.py
chemicals/viscosity.py
chemicals/volume.py
chemicals/Critical Properties/Appendix to PSRK Revision 4.tsv
chemicals/Critical Properties/CRCCriticalOrganics.tsv
chemicals/Critical Properties/DIPPRPinaMartines.tsv
chemicals/Critical Properties/IUPACOrganicCriticalProps.tsv
chemicals/Critical Properties/Mathews1972InorganicCriticalProps.tsv
chemicals/Critical Properties/PassutDanner1973.tsv
chemicals/Critical Properties/Yaws Collection.tsv
chemicals/Critical Properties/fedors_Vc_predictions.tsv
chemicals/Critical Properties/omega_Psat_Tc_predictions.tsv
chemicals/Critical Properties/wilson_jasperson_Tc_Pc_predictions.tsv
chemicals/Density/COSTALD Parameters.tsv
chemicals/Density/CRC Inorganics densties of molten compounds and salts.tsv
chemicals/Density/CRC Liquid Inorganic Constant Densities.tsv
chemicals/Density/CRC Solid Inorganic Constant Densities.tsv
chemicals/Density/CRC Virial polynomials.tsv
chemicals/Density/Mchaweh SN0 deltas.tsv
chemicals/Density/Perry Parameters 105.tsv
chemicals/Density/VDI PPDS Density of Saturated Liquids.tsv
chemicals/Electrolytes/CRC Thermodynamic Properties of Aqueous Ions.tsv
chemicals-1.4.0.dist-info/licenses/AUTHORS
chemicals-1.4.0.dist-info/licenses/LICENSE.txt
chemicals-1.4.0.dist-info/METADATA
chemicals-1.4.0.dist-info/WHEEL
chemicals-1.4.0.dist-info/top_level.txt
chemicals-1.4.0.dist-info/RECORD
